colorsofmotion/__init__.py
colorsofmotion-1.0.3.dist-info/LICENSE
colorsofmotion-1.0.3.dist-info/METADATA
colorsofmotion-1.0.3.dist-info/WHEEL
colorsofmotion-1.0.3.dist-info/entry_points.txt
colorsofmotion-1.0.3.dist-info/top_level.txt
colorsofmotion-1.0.3.dist-info/RECORD
