Metadata-Version: 2.1
Name: colorsofmotion
Version: 1.0.3
Summary: CLI-script to achieve colors of motion effect
Home-page: https://github.com/Lusori0/colorsofmotion
Author: Lusorio
Author-email: manuel.buenstorf@gmail.com
License: MIT
Keywords: colorsofmotion video poster
Platform: UNKNOWN
Classifier: Programming Language :: Python :: 3
Classifier: License :: OSI Approved :: MIT License
Classifier: Operating System :: OS Independent
Requires-Dist: moviepy (>=1.0.2)
Requires-Dist: Pillow (>=7.1.2)
Requires-Dist: numpy (>=1.18.5)
